snowpark_extensions/__init__.py
snowpark_extensions/dataframe_extensions.py
snowpark_extensions/dataframe_reader_extensions.py
snowpark_extensions/dataframe_reader_extensions_csv.py
snowpark_extensions/functions_extensions.py
snowpark_extensions/logging_utils.py
snowpark_extensions/session_builder_extensions.py
snowpark_extensions/session_extensions.py
snowpark_extensions/types_extensions.py
snowpark_extensions/utils.py
snowpark_extensions-0.0.47.dist-info/METADATA
snowpark_extensions-0.0.47.dist-info/WHEEL
snowpark_extensions-0.0.47.dist-info/top_level.txt
snowpark_extensions-0.0.47.dist-info/RECORD
