Metadata-Version: 2.4
Name: snowpark_extensions
Version: 0.0.47
Summary: A set of helpers to extend snowpark functionality. NOTE: most of this extensions are already available in the official snowpark python package
Home-page: https://github.com/Snowflake-Labs/snowpark-extensions-py
Author: mauricio.rojas
Author-email: mauricio.rojas@snowflake.com
Requires-Dist: snowflake-snowpark-python[pandas]>=1.31.1
Requires-Dist: jinja2
Dynamic: author
Dynamic: author-email
Dynamic: description
Dynamic: description-content-type
Dynamic: home-page
Dynamic: requires-dist
Dynamic: summary
